konta/__init__.py
konta/__main__.py
konta/bean_import.py
konta/config.py
konta/woob_import.py
konta/woob_to_bean.py
konta-0.3.0.dist-info/LICENSE
konta-0.3.0.dist-info/WHEEL
konta-0.3.0.dist-info/METADATA
konta-0.3.0.dist-info/RECORD
