Metadata-Version: 2.1
Name: konta
Version: 0.3.0
Summary: A Woob Bank -> Beancount data pipeline.
Author-email: Gerry Agbobada <pypi@gagbo.net>
Requires-Python: >=3.7,<4
Classifier: License :: OSI Approved :: MIT License
Requires-Dist: woob >=3.0
Requires-Dist: beancount >=2.3.5
Requires-Dist: toml >=0.10.2
Requires-Dist: xdg >=5.1.1
Project-URL: Documentation, https://git.sr.ht/~gagbo/PyKonta
Project-URL: Home, https://git.sr.ht/~gagbo/PyKonta
Project-URL: Source, https://git.sr.ht/~gagbo/PyKonta
